wfl/__init__.py
wfl/__version__.py
wfl/configset.py
wfl/descriptor_heuristics.py
wfl/map.py
wfl/autoparallelize/__init__.py
wfl/autoparallelize/autoparainfo.py
wfl/autoparallelize/base.py
wfl/autoparallelize/mpipool_support.py
wfl/autoparallelize/pool.py
wfl/autoparallelize/remote.py
wfl/autoparallelize/remoteinfo.py
wfl/autoparallelize/utils.py
wfl/calculators/__init__.py
wfl/calculators/aims.py
wfl/calculators/castep.py
wfl/calculators/committee.py
wfl/calculators/espresso.py
wfl/calculators/generic.py
wfl/calculators/kpts.py
wfl/calculators/mopac.py
wfl/calculators/utils.py
wfl/calculators/vasp.py
wfl/calculators/wfl_fileio_calculator.py
wfl/calculators/orca/__init__.py
wfl/calculators/orca/basinhopping.py
wfl/cli/__init__.py
wfl/cli/cli.py
wfl/cli/cli_options.py
wfl/cli/dft_convergence_test.py
wfl/cli/gap_rss_iter_fit.py
wfl/cli/commands/__init__.py
wfl/cli/commands/descriptor.py
wfl/cli/commands/error.py
wfl/cli/commands/eval.py
wfl/cli/commands/generate.py
wfl/cli/commands/select.py
wfl/descriptors/__init__.py
wfl/descriptors/quippy.py
wfl/fit/__init__.py
wfl/fit/ace.py
wfl/fit/error.py
wfl/fit/mace.py
wfl/fit/utils.py
wfl/fit/gap/__init__.py
wfl/fit/gap/glue_2b.py
wfl/fit/gap/multistage.py
wfl/fit/gap/relocate.py
wfl/fit/gap/simple.py
wfl/fit/modify_database/__init__.py
wfl/fit/modify_database/gap_rss_set_config_sigmas_from_convex_hull.py
wfl/fit/modify_database/scale_orig.py
wfl/fit/modify_database/simple_factor_nonperiodic.py
wfl/generate/__init__.py
wfl/generate/atoms_and_dimers.py
wfl/generate/buildcell.py
wfl/generate/minimahopping.py
wfl/generate/neb.py
wfl/generate/normal_modes.py
wfl/generate/optimize.py
wfl/generate/phonopy.py
wfl/generate/smiles.py
wfl/generate/supercells.py
wfl/generate/utils.py
wfl/generate/md/__init__.py
wfl/generate/md/abort.py
wfl/generate/md/abort_base.py
wfl/generate/md/utils.py
wfl/select/__init__.py
wfl/select/by_descriptor.py
wfl/select/convex_hull.py
wfl/select/flat_histogram.py
wfl/select/selection_space.py
wfl-0.3.5.dist-info/licenses/LICENSE
wfl-0.3.5.dist-info/METADATA
wfl-0.3.5.dist-info/WHEEL
wfl-0.3.5.dist-info/entry_points.txt
wfl-0.3.5.dist-info/top_level.txt
wfl-0.3.5.dist-info/RECORD
