Metadata-Version: 2.4
Name: wfl
Version: 0.3.5
License:                     GNU GENERAL PUBLIC LICENSE
Requires-Python: >=3.9
License-File: LICENSE
Requires-Dist: click>=7.0
Requires-Dist: numpy<2
Requires-Dist: ase>=3.22.1
Requires-Dist: pyyaml
Requires-Dist: spglib
Requires-Dist: docstring_parser
Requires-Dist: expyre-wfl
Requires-Dist: universalSOAP
Requires-Dist: pandas
Provides-Extra: test
Requires-Dist: pytest; extra == "test"
Requires-Dist: mace-torch; extra == "test"
Requires-Dist: quippy-ase; extra == "test"
Requires-Dist: requests; extra == "test"
Requires-Dist: rdkit==2024.3.3; extra == "test"
Provides-Extra: doc
Requires-Dist: sphinx; extra == "doc"
Requires-Dist: sphinx_click; extra == "doc"
Requires-Dist: nbsphinx; extra == "doc"
Requires-Dist: myst_parser; extra == "doc"
Requires-Dist: sphinx_book_theme; extra == "doc"
Provides-Extra: all
Requires-Dist: wfl[doc,test]; extra == "all"
Dynamic: license-file
